hein_utilities/__init__.py
hein_utilities/control_manager.py
hein_utilities/datetime_utilities.py
hein_utilities/files.py
hein_utilities/json_utilities.py
hein_utilities/misc.py
hein_utilities/runnable.py
hein_utilities/slackbot.py
hein_utilities/temporal_data.py
hein_utilities/slack_integration/__init__.py
hein_utilities/slack_integration/bots.py
hein_utilities/slack_integration/logging.py
hein_utilities/slack_integration/parsing.py
hein_utilities/slack_integration/slack_managers.py
tests/__init__.py
tests/json_utilities_test.py
tests/test_temporal_data.py
tests/test_watcher.py
hein_utilities-3.14.2.dist-info/LICENSE
hein_utilities-3.14.2.dist-info/METADATA
hein_utilities-3.14.2.dist-info/WHEEL
hein_utilities-3.14.2.dist-info/top_level.txt
hein_utilities-3.14.2.dist-info/RECORD
