Metadata-Version: 2.1
Name: hein-utilities
Version: 3.14.2
Summary: Methods and Classes used in a variety of Hein projects
Home-page: https://gitlab.com/heingroup/hein_utilities
Author: Lars Yunker / Hein Group
License: Copyright 2019 Lars Yunker / Hein Group        
Project-URL: Documentation, https://hein-utilities.readthedocs.io/en/latest/
Project-URL: Hein Group, https://groups.chem.ubc.ca/jheints1/
Platform: UNKNOWN
Classifier: Programming Language :: Python :: 3
Classifier: License :: OSI Approved :: MIT License
Classifier: Development Status :: 4 - Beta
Classifier: Intended Audience :: Science/Research
Classifier: Topic :: Scientific/Engineering :: Chemistry
Classifier: Topic :: Scientific/Engineering :: Information Analysis
Classifier: Operating System :: Microsoft :: Windows
Classifier: Natural Language :: English
Requires-Python: >=3.6
License-File: LICENSE
Requires-Dist: numpy
Requires-Dist: slackclient
Requires-Dist: pandas
